{"rating": "7.8", "episodes": {"1": [{"date": null, "rating": "8.2", "episode-num": "1", "episode-name": "A Stitch in Time"}, {"date": null, "rating": "8.0", "episode-num": "2", "episode-name": "Fast Times"}, {"date": null, "rating": "7.8", "episode-num": "3", "episode-name": "Wasting Time"}, {"date": null, "rating": "7.8", "episode-num": "4", "episode-name": "Matter of Time"}, {"date": null, "rating": "8.0", "episode-num": "5", "episode-name": "A Test of Time"}, {"date": null, "rating": "7.7", "episode-num": "6", "episode-name": "Time's Up"}, {"date": null, "rating": "7.9", "episode-num": "7", "episode-name": "The Politics of Time"}, {"date": null, "rating": "8.0", "episode-num": "8", "episode-name": "Playtime"}, {"date": null, "rating": "8.3", "episode-num": "9", "episode-name": "Family Time"}, {"date": null, "rating": "8.8", "episode-num": "10", "episode-name": "End Times"}], "3": [{"date": null, "rating": "8.5", "episode-num": "1", "episode-name": "Minute by Minute"}, {"date": null, "rating": "8.2", "episode-num": "2", "episode-name": "Minute Man"}, {"date": null, "rating": "8.1", "episode-num": "3", "episode-name": "Minute to Win It"}, {"date": null, "rating": "8.0", "episode-num": "4", "episode-name": "Minute Changes"}, {"date": null, "rating": "7.8", "episode-num": "5", "episode-name": "30 Minutes to Air"}, {"date": null, "rating": "7.8", "episode-num": "6", "episode-name": "Wasted Minute"}, {"date": null, "rating": "8.1", "episode-num": "7", "episode-name": "Waning Minute"}, {"date": null, "rating": "8.1", "episode-num": "8", "episode-name": "So Do Our Minutes Hasten"}, {"date": null, "rating": "8.2", "episode-num": "9", "episode-name": "Minute of Silence"}, {"date": null, "rating": "8.0", "episode-num": "10", "episode-name": "Revolutions Per Minute"}, {"date": null, "rating": "8.9", "episode-num": "11", "episode-name": "3 Minutes to Midnight"}, {"date": null, "rating": "8.4", "episode-num": "12", "episode-name": "The Dying Minutes"}, {"date": null, "rating": "8.8", "episode-num": "13", "episode-name": "Last Minute"}], "2": [{"date": null, "rating": "8.0", "episode-num": "1", "episode-name": "Second Chances"}, {"date": null, "rating": "7.9", "episode-num": "2", "episode-name": "Split Second"}, {"date": null, "rating": "7.7", "episode-num": "3", "episode-name": "Second Thoughts"}, {"date": null, "rating": "8.2", "episode-num": "4", "episode-name": "Second Skin"}, {"date": null, "rating": "8.1", "episode-num": "5", "episode-name": "Second Opinion"}, {"date": null, "rating": "8.3", "episode-num": "6", "episode-name": "Second Truths"}, {"date": null, "rating": "8.1", "episode-num": "7", "episode-name": "Second Degree"}, {"date": null, "rating": "8.2", "episode-num": "8", "episode-name": "Second Listen"}, {"date": null, "rating": "7.9", "episode-num": "9", "episode-name": "Seconds"}, {"date": null, "rating": "8.1", "episode-num": "10", "episode-name": "Second Wave"}, {"date": null, "rating": "8.2", "episode-num": "11", "episode-name": "Second Guess"}, {"date": null, "rating": "8.5", "episode-num": "12", "episode-name": "Second Last"}, {"date": null, "rating": "8.9", "episode-num": "13", "episode-name": "Second Time"}], "4": [{"date": null, "rating": null, "episode-num": "1", "episode-name": "Episode #4.1"}, {"date": null, "rating": null, "episode-num": "2", "episode-name": "Episode #4.2"}, {"date": null, "rating": null, "episode-num": "3", "episode-name": "Episode #4.3"}, {"date": null, "rating": null, "episode-num": "4", "episode-name": "Episode #4.4"}, {"date": null, "rating": null, "episode-num": "5", "episode-name": "Episode #4.5"}, {"date": null, "rating": null, "episode-num": "6", "episode-name": "Episode #4.6"}]}, "name": "Continuum"}