{"rating": "9.4", "episodes": {"1": [{"date": "2 Jun. 2002", "rating": "8.1", "episode-num": "1", "episode-name": "The Target"}, {"date": "9 Jun. 2002", "rating": "8.4", "episode-num": "2", "episode-name": "The Detail"}, {"date": "16 Jun. 2002", "rating": "8.4", "episode-num": "3", "episode-name": "The Buys"}, {"date": "23 Jun. 2002", "rating": "8.4", "episode-num": "4", "episode-name": "Old Cases"}, {"date": "30 Jun. 2002", "rating": "8.5", "episode-num": "5", "episode-name": "The Pager"}, {"date": "7 Jul. 2002", "rating": "8.8", "episode-num": "6", "episode-name": "The Wire"}, {"date": "21 Jul. 2002", "rating": "8.7", "episode-num": "7", "episode-name": "One Arrest"}, {"date": "28 Jul. 2002", "rating": "8.7", "episode-num": "8", "episode-name": "Lessons"}, {"date": "4 Aug. 2002", "rating": "8.8", "episode-num": "9", "episode-name": "Game Day"}, {"date": "11 Aug. 2002", "rating": "9.1", "episode-num": "10", "episode-name": "The Cost"}, {"date": "18 Aug. 2002", "rating": "8.9", "episode-num": "11", "episode-name": "The Hunt"}, {"date": "1 Sep. 2002", "rating": "9.1", "episode-num": "12", "episode-name": "Cleaning Up"}, {"date": "8 Sep. 2002", "rating": "9.0", "episode-num": "13", "episode-name": "Sentencing"}], "3": [{"date": "19 Sep. 2004", "rating": "8.3", "episode-num": "1", "episode-name": "Time After Time"}, {"date": "27 Sep. 2004", "rating": "8.6", "episode-num": "2", "episode-name": "All Due Respect"}, {"date": "3 Oct. 2004", "rating": "8.6", "episode-num": "3", "episode-name": "Dead Soldiers"}, {"date": "10 Oct. 2004", "rating": "8.7", "episode-num": "4", "episode-name": "Hamsterdam"}, {"date": "17 Oct. 2004", "rating": "8.8", "episode-num": "5", "episode-name": "Straight and True"}, {"date": "31 Oct. 2004", "rating": "8.8", "episode-num": "6", "episode-name": "Homecoming"}, {"date": "7 Nov. 2004", "rating": "8.8", "episode-num": "7", "episode-name": "Back Burners"}, {"date": "14 Nov. 2004", "rating": "8.9", "episode-num": "8", "episode-name": "Moral Midgetry"}, {"date": "21 Nov. 2004", "rating": "8.8", "episode-num": "9", "episode-name": "Slapstick"}, {"date": "28 Nov. 2004", "rating": "8.9", "episode-num": "10", "episode-name": "Reformation"}, {"date": "12 Dec. 2004", "rating": "9.1", "episode-num": "11", "episode-name": "Middle Ground"}, {"date": "19 Dec. 2004", "rating": "9.1", "episode-num": "12", "episode-name": "Mission Accomplished"}], "2": [{"date": "1 Jun. 2003", "rating": "8.1", "episode-num": "1", "episode-name": "Ebb Tide"}, {"date": "8 Jun. 2003", "rating": "8.3", "episode-num": "2", "episode-name": "Collateral Damage"}, {"date": "15 Jun. 2003", "rating": "8.4", "episode-num": "3", "episode-name": "Hot Shots"}, {"date": "22 Jun. 2003", "rating": "8.3", "episode-num": "4", "episode-name": "Hard Cases"}, {"date": "29 Jun. 2003", "rating": "8.4", "episode-num": "5", "episode-name": "Undertow"}, {"date": "6 Jul. 2003", "rating": "8.9", "episode-num": "6", "episode-name": "All Prologue"}, {"date": "13 Jul. 2003", "rating": "8.5", "episode-num": "7", "episode-name": "Backwash"}, {"date": "27 Jul. 2003", "rating": "8.7", "episode-num": "8", "episode-name": "Duck and Cover"}, {"date": "3 Aug. 2003", "rating": "8.8", "episode-num": "9", "episode-name": "Stray Rounds"}, {"date": "10 Aug. 2003", "rating": "9.1", "episode-num": "10", "episode-name": "Storm Warnings"}, {"date": "17 Aug. 2003", "rating": "9.1", "episode-num": "11", "episode-name": "Bad Dreams"}, {"date": "24 Aug. 2003", "rating": "9.1", "episode-num": "12", "episode-name": "Port in a Storm"}], "5": [{"date": "6 Jan. 2008", "rating": "8.4", "episode-num": "1", "episode-name": "More with Less"}, {"date": "13 Jan. 2008", "rating": "8.5", "episode-num": "2", "episode-name": "Unconfirmed Reports"}, {"date": "20 Jan. 2008", "rating": "8.7", "episode-num": "3", "episode-name": "Not for Attribution"}, {"date": "27 Jan. 2008", "rating": "9.0", "episode-num": "4", "episode-name": "Transitions"}, {"date": "3 Feb. 2008", "rating": "8.8", "episode-num": "5", "episode-name": "React Quotes"}, {"date": "10 Feb. 2008", "rating": "8.7", "episode-num": "6", "episode-name": "The Dickensian Aspect"}, {"date": "17 Feb. 2008", "rating": "8.7", "episode-num": "7", "episode-name": "Took"}, {"date": "24 Feb. 2008", "rating": "8.9", "episode-num": "8", "episode-name": "Clarifications"}, {"date": "2 Mar. 2008", "rating": "9.1", "episode-num": "9", "episode-name": "Late Editions"}, {"date": "9 Mar. 2008", "rating": "9.1", "episode-num": "10", "episode-name": "-30-"}], "4": [{"date": "10 Sep. 2006", "rating": "8.6", "episode-num": "1", "episode-name": "Boys of Summer"}, {"date": "17 Sep. 2006", "rating": "8.6", "episode-num": "2", "episode-name": "Soft Eyes"}, {"date": "24 Sep. 2006", "rating": "8.8", "episode-num": "3", "episode-name": "Home Rooms"}, {"date": "1 Oct. 2006", "rating": "8.6", "episode-num": "4", "episode-name": "Refugees"}, {"date": "8 Oct. 2006", "rating": "8.7", "episode-num": "5", "episode-name": "Alliances"}, {"date": "15 Oct. 2006", "rating": "8.8", "episode-num": "6", "episode-name": "Margin of Error"}, {"date": "29 Oct. 2006", "rating": "8.7", "episode-num": "7", "episode-name": "Unto Others"}, {"date": "5 Nov. 2006", "rating": "8.7", "episode-num": "8", "episode-name": "Corner Boys"}, {"date": "12 Nov. 2006", "rating": "8.7", "episode-num": "9", "episode-name": "Know Your Place"}, {"date": "19 Nov. 2006", "rating": "8.9", "episode-num": "10", "episode-name": "Misgivings"}, {"date": "26 Nov. 2006", "rating": "9.1", "episode-num": "11", "episode-name": "A New Day"}, {"date": "3 Dec. 2006", "rating": "9.1", "episode-num": "12", "episode-name": "That's Got His Own"}, {"date": "10 Dec. 2006", "rating": "9.1", "episode-num": "13", "episode-name": "Final Grades"}]}, "name": "The Wire"}